tinyquant_cli/__init__.py
tinyquant_cli/cli.py
tinyquant_cli-0.1.1.dist-info/licenses/LICENSE
tinyquant_cli-0.1.1.dist-info/METADATA
tinyquant_cli-0.1.1.dist-info/WHEEL
tinyquant_cli-0.1.1.dist-info/entry_points.txt
tinyquant_cli-0.1.1.dist-info/top_level.txt
tinyquant_cli-0.1.1.dist-info/RECORD
